foalorm/__init__.py
foalorm/converting.py
foalorm/options.py
foalorm/py23compat.py
foalorm/flask/__init__.py
foalorm/flask/example/__init__.py
foalorm/flask/example/__main__.py
foalorm/flask/example/app.py
foalorm/flask/example/config.py
foalorm/flask/example/models.py
foalorm/flask/example/views.py
foalorm/flask/example/templates/index.html
foalorm/flask/example/templates/login.html
foalorm/flask/example/templates/reg.html
foalorm/orm/__init__.py
foalorm/orm/asttranslation.py
foalorm/orm/core.py
foalorm/orm/dbapiprovider.py
foalorm/orm/dbschema.py
foalorm/orm/decompiling.py
foalorm/orm/ormtypes.py
foalorm/orm/serialization.py
foalorm/orm/sqlbuilding.py
foalorm/orm/sqlsymbols.py
foalorm/orm/sqltranslation.py
foalorm/orm/dbproviders/__init__.py
foalorm/orm/dbproviders/cockroach.py
foalorm/orm/dbproviders/mysql.py
foalorm/orm/dbproviders/oracle.py
foalorm/orm/dbproviders/postgres.py
foalorm/orm/dbproviders/sqlite.py
foalorm/orm/examples/__init__.py
foalorm/orm/examples/bottle_example.py
foalorm/orm/examples/compositekeys.py
foalorm/orm/examples/demo.py
foalorm/orm/examples/estore.py
foalorm/orm/examples/inheritance1.py
foalorm/orm/examples/test_numbers.py
foalorm/orm/examples/university1.py
foalorm/orm/examples/university2.py
foalorm/orm/integration/__init__.py
foalorm/orm/integration/bottle_plugin.py
foalorm/orm/tests/__init__.py
foalorm/orm/tests/fixtures.py
foalorm/orm/tests/model1.py
foalorm/orm/tests/queries.txt
foalorm/orm/tests/sql_tests.py
foalorm/orm/tests/test_array.py
foalorm/orm/tests/test_attribute_options.py
foalorm/orm/tests/test_autostrip.py
foalorm/orm/tests/test_buffer.py
foalorm/orm/tests/test_bug_170.py
foalorm/orm/tests/test_bug_182.py
foalorm/orm/tests/test_bug_331.py
foalorm/orm/tests/test_bug_386.py
foalorm/orm/tests/test_cascade.py
foalorm/orm/tests/test_cascade_delete.py
foalorm/orm/tests/test_collections.py
foalorm/orm/tests/test_conversions.py
foalorm/orm/tests/test_core_find_in_cache.py
foalorm/orm/tests/test_core_multiset.py
foalorm-0.1.0.dist-info/METADATA
foalorm-0.1.0.dist-info/WHEEL
foalorm-0.1.0.dist-info/top_level.txt
foalorm-0.1.0.dist-info/RECORD
